fair_async_rlock/__init__.py
fair_async_rlock/fair_async_rlock.py
fair_async_rlock/tests/__init__.py
fair_async_rlock/tests/test_fair_async_rlock.py
fair_async_rlock-1.0.6.dist-info/LICENSE
fair_async_rlock-1.0.6.dist-info/METADATA
fair_async_rlock-1.0.6.dist-info/WHEEL
fair_async_rlock-1.0.6.dist-info/top_level.txt
fair_async_rlock-1.0.6.dist-info/RECORD
