Metadata-Version: 2.1
Name: fair-async-rlock
Version: 1.0.6
Summary: A well-tested implementation of a fair asynchronous RLock for concurrent programming.
Home-page: https://github.com/Joshuaalbert/FairAsyncRLock
Author: Joshua G. Albert
Author-email: albert@strw.leidenuniv.nl
Classifier: Programming Language :: Python :: 3
Classifier: License :: OSI Approved :: Apache Software License
Classifier: Operating System :: OS Independent
Requires-Python: >=3.7
License-File: LICENSE
